hub_search/__init__.py
hub_search/clean.py
hub_search/cli.py
hub_search/search.py
hub_search/task.py
hub_search/verify.py
hub_search-0.1.2.dist-info/METADATA
hub_search-0.1.2.dist-info/WHEEL
hub_search-0.1.2.dist-info/entry_points.txt
hub_search-0.1.2.dist-info/RECORD
