Metadata-Version: 2.4
Name: hub-search
Version: 0.1.2
Summary: A CLI tool to search, clean, and verify sensitive info on GitHub.
Author-email: Your Name <your.email@example.com>
License: MIT
Requires-Python: >=3.9
Requires-Dist: openai>=1.0.0
Requires-Dist: requests>=2.31.0
